Metadata-Version: 1.0
Name: mathoperations-arva
Version: 0.1
Summary: Gaussian distributions
Home-page: UNKNOWN
Author: Aravindh Vangal
Author-email: aravindh1987@gmail.com
License: UNKNOWN
Platform: UNKNOWN
